[
  {
    "_id": "614f551ba84d19e0954ba82c",
    "_class": "core:class:TxCreateDoc",
    "space": "core:space:Tx",
    "objectId": "core:class:Obj",
    "objectClass": "core:class:Class",
    "objectSpace": "core:space:Model",
    "modifiedOn": 1632589083743,
    "modifiedBy": "core:account:System",
    "attributes": {
      "kind": 0
    }
  },
  {
    "_id": "614f551ba84d19e0954ba82d",
    "_class": "core:class:TxCreateDoc",
    "space": "core:space:Tx",
    "objectId": "core:class:Doc",
    "objectClass": "core:class:Class",
    "objectSpace": "core:space:Model",
    "modifiedOn": 1632589083743,
    "modifiedBy": "core:account:System",
    "attributes": {
      "kind": 0,
      "extends": "core:class:Obj"
    }
  },
  {
    "_id": "614f551ba84d19e0954ba82e",
    "_class": "core:class:TxCreateDoc",
    "space": "core:space:Tx",
    "objectId": "core:class:State",
    "objectClass": "core:class:Class",
    "objectSpace": "core:space:Model",
    "modifiedOn": 1632589083743,
    "modifiedBy": "core:account:System",
    "attributes": {
      "domain": "state",
      "kind": 0,
      "extends": "core:class:Doc"
    }
  },
  {
    "_id": "614f551ba84d19e0954ba82f",
    "_class": "core:class:TxCreateDoc",
    "space": "core:space:Tx",
    "objectId": "core:class:Type",
    "objectClass": "core:class:Class",
    "objectSpace": "core:space:Model",
    "modifiedOn": 1632589083743,
    "modifiedBy": "core:account:System",
    "attributes": {
      "kind": 0,
      "extends": "core:class:Doc"
    }
  },
  {
    "_id": "614f551ba84d19e0954ba830",
    "_class": "core:class:TxCreateDoc",
    "space": "core:space:Tx",
    "objectId": "core:class:TypeString",
    "objectClass": "core:class:Class",
    "objectSpace": "core:space:Model",
    "modifiedOn": 1632589083743,
    "modifiedBy": "core:account:System",
    "attributes": {
      "kind": 0,
      "extends": "core:class:Type"
    }
  },
  {
    "_id": "614f551ba84d19e0954ba831",
    "_class": "core:class:TxCreateDoc",
    "space": "core:space:Tx",
    "objectId": "core:class:Attribute",
    "objectClass": "core:class:Class",
    "objectSpace": "core:space:Model",
    "modifiedOn": 1632589083743,
    "modifiedBy": "core:account:System",
    "attributes": {
      "kind": 0,
      "extends": "core:class:Doc"
    }
  },
  {
    "_id": "614f551ba84d19e0954ba832",
    "_class": "core:class:TxCreateDoc",
    "space": "core:space:Tx",
    "objectId": "core:class:Account",
    "objectClass": "core:class:Class",
    "objectSpace": "core:space:Model",
    "modifiedOn": 1632589083743,
    "modifiedBy": "core:account:System",
    "attributes": {
      "domain": "model",
      "kind": 0,
      "extends": "core:class:Doc"
    }
  },
  {
    "_id": "614f551ba84d19e0954ba833",
    "_class": "core:class:TxCreateDoc",
    "space": "core:space:Tx",
    "objectId": "core:class:Space",
    "objectClass": "core:class:Class",
    "objectSpace": "core:space:Model",
    "modifiedOn": 1632589083743,
    "modifiedBy": "core:account:System",
    "attributes": {
      "domain": "model",
      "kind": 0,
      "extends": "core:class:Doc"
    }
  },
  {
    "_id": "614f551ba84d19e0954ba834",
    "_class": "core:class:TxCreateDoc",
    "space": "core:space:Tx",
    "objectId": "core:class:SpaceWithStates",
    "objectClass": "core:class:Class",
    "objectSpace": "core:space:Model",
    "modifiedOn": 1632589083743,
    "modifiedBy": "core:account:System",
    "attributes": {
      "kind": 0,
      "extends": "core:class:Space"
    }
  },
  {
    "_id": "614f551ba84d19e0954ba835",
    "_class": "core:class:TxCreateDoc",
    "space": "core:space:Tx",
    "objectId": "core:class:Tx",
    "objectClass": "core:class:Class",
    "objectSpace": "core:space:Model",
    "modifiedOn": 1632589083743,
    "modifiedBy": "core:account:System",
    "attributes": {
      "domain": "tx",
      "kind": 0,
      "extends": "core:class:Doc"
    }
  },
  {
    "_id": "614f551ba84d19e0954ba836",
    "_class": "core:class:TxCreateDoc",
    "space": "core:space:Tx",
    "objectId": "core:class:TxCUD",
    "objectClass": "core:class:Class",
    "objectSpace": "core:space:Model",
    "modifiedOn": 1632589083743,
    "modifiedBy": "core:account:System",
    "attributes": {
      "kind": 0,
      "extends": "core:class:Tx"
    }
  },
  {
    "_id": "614f551ba84d19e0954ba837",
    "_class": "core:class:TxCreateDoc",
    "space": "core:space:Tx",
    "objectId": "core:class:TxRemoveDoc",
    "objectClass": "core:class:Class",
    "objectSpace": "core:space:Model",
    "modifiedOn": 1632589083743,
    "modifiedBy": "core:account:System",
    "attributes": {
      "kind": 0,
      "extends": "core:class:TxCUD"
    }
  },
  {
    "_id": "614f551ba84d19e0954ba838",
    "_class": "core:class:TxCreateDoc",
    "space": "core:space:Tx",
    "objectId": "core:class:TxUpdateDoc",
    "objectClass": "core:class:Class",
    "objectSpace": "core:space:Model",
    "modifiedOn": 1632589083743,
    "modifiedBy": "core:account:System",
    "attributes": {
      "kind": 0,
      "extends": "core:class:TxCUD"
    }
  },
  {
    "_id": "614f551ba84d19e0954ba839",
    "_class": "core:class:TxCreateDoc",
    "space": "core:space:Tx",
    "objectId": "core:class:TxMixin",
    "objectClass": "core:class:Class",
    "objectSpace": "core:space:Model",
    "modifiedOn": 1632589083743,
    "modifiedBy": "core:account:System",
    "attributes": {
      "kind": 0,
      "extends": "core:class:TxCUD"
    }
  },
  {
    "_id": "614f551ba84d19e0954ba83a",
    "_class": "core:class:TxCreateDoc",
    "space": "core:space:Tx",
    "objectId": "core:class:TxPutBag",
    "objectClass": "core:class:Class",
    "objectSpace": "core:space:Model",
    "modifiedOn": 1632589083743,
    "modifiedBy": "core:account:System",
    "attributes": {
      "kind": 0,
      "extends": "core:class:TxCUD"
    }
  },
  {
    "_id": "614f551ba84d19e0954ba83b",
    "_class": "core:class:TxCreateDoc",
    "space": "core:space:Tx",
    "objectId": "core:class:TxCreateDoc",
    "objectClass": "core:class:Class",
    "objectSpace": "core:space:Model",
    "modifiedOn": 1632589083743,
    "modifiedBy": "core:account:System",
    "attributes": {
      "kind": 0,
      "extends": "core:class:TxCUD"
    }
  },
  {
    "_id": "614f551ba84d19e0954ba83c",
    "_class": "core:class:TxCreateDoc",
    "space": "core:space:Tx",
    "objectId": "core:class:Class",
    "objectClass": "core:class:Class",
    "objectSpace": "core:space:Model",
    "modifiedOn": 1632589083743,
    "modifiedBy": "core:account:System",
    "attributes": {
      "domain": "model",
      "kind": 0,
      "extends": "core:class:Doc"
    }
  },
  {
    "_id": "614f551ba84d19e0954ba83d",
    "_class": "core:class:TxCreateDoc",
    "space": "core:space:Tx",
    "objectId": "core:class:Mixin",
    "objectClass": "core:class:Class",
    "objectSpace": "core:space:Model",
    "modifiedOn": 1632589083743,
    "modifiedBy": "core:account:System",
    "attributes": {
      "kind": 0,
      "extends": "core:class:Class"
    }
  },
  {
    "_id": "614f551ba84d19e0954ba83e",
    "_class": "core:class:TxCreateDoc",
    "space": "core:space:Tx",
    "objectId": "view:class:ActionTarget",
    "objectClass": "core:class:Class",
    "objectSpace": "core:space:Model",
    "modifiedOn": 1632589083743,
    "modifiedBy": "core:account:System",
    "attributes": {
      "domain": "model",
      "kind": 0,
      "extends": "core:class:Doc"
    }
  },
  {
    "_id": "614f551ba84d19e0954ba83f",
    "_class": "core:class:TxCreateDoc",
    "space": "core:space:Tx",
    "objectId": "view:class:Action",
    "objectClass": "core:class:Class",
    "objectSpace": "core:space:Model",
    "modifiedOn": 1632589083743,
    "modifiedBy": "core:account:System",
    "attributes": {
      "domain": "model",
      "kind": 0,
      "extends": "core:class:Doc"
    }
  },
  {
    "_id": "614f551ba84d19e0954ba840",
    "_class": "core:class:TxCreateDoc",
    "space": "core:space:Tx",
    "objectId": "view:class:Viewlet",
    "objectClass": "core:class:Class",
    "objectSpace": "core:space:Model",
    "modifiedOn": 1632589083743,
    "modifiedBy": "core:account:System",
    "attributes": {
      "domain": "model",
      "kind": 0,
      "extends": "core:class:Doc"
    }
  },
  {
    "_id": "614f551ba84d19e0954ba841",
    "_class": "core:class:TxCreateDoc",
    "space": "core:space:Tx",
    "objectId": "view:class:ViewletDescriptor",
    "objectClass": "core:class:Class",
    "objectSpace": "core:space:Model",
    "modifiedOn": 1632589083743,
    "modifiedBy": "core:account:System",
    "attributes": {
      "domain": "model",
      "kind": 0,
      "extends": "core:class:Doc"
    }
  },
  {
    "_id": "614f551ba84d19e0954ba842",
    "_class": "core:class:TxCreateDoc",
    "space": "core:space:Tx",
    "objectId": "view:mixin:ObjectEditor",
    "objectClass": "core:class:Class",
    "objectSpace": "core:space:Model",
    "modifiedOn": 1632589083743,
    "modifiedBy": "core:account:System",
    "attributes": {
      "kind": 0,
      "extends": "core:class:Class"
    }
  },
  {
    "_id": "614f551ba84d19e0954ba843",
    "_class": "core:class:TxCreateDoc",
    "space": "core:space:Tx",
    "objectId": "view:mixin:KanbanCard",
    "objectClass": "core:class:Class",
    "objectSpace": "core:space:Model",
    "modifiedOn": 1632589083743,
    "modifiedBy": "core:account:System",
    "attributes": {
      "kind": 0,
      "extends": "core:class:Class"
    }
  },
  {
    "_id": "614f551ba84d19e0954ba844",
    "_class": "core:class:TxCreateDoc",
    "space": "core:space:Tx",
    "objectId": "view:mixin:AttributePresenter",
    "objectClass": "core:class:Class",
    "objectSpace": "core:space:Model",
    "modifiedOn": 1632589083743,
    "modifiedBy": "core:account:System",
    "attributes": {
      "kind": 0,
      "extends": "core:class:Class"
    }
  },
  {
    "_id": "614f551ba84d19e0954ba845",
    "_class": "core:class:TxCreateDoc",
    "space": "core:space:Tx",
    "objectId": "view:mixin:AttributeEditor",
    "objectClass": "core:class:Class",
    "objectSpace": "core:space:Model",
    "modifiedOn": 1632589083743,
    "modifiedBy": "core:account:System",
    "attributes": {
      "kind": 0,
      "extends": "core:class:Class"
    }
  },
  {
    "_id": "614f551ba84d19e0954ba846",
    "_class": "core:class:TxMixin",
    "space": "core:space:Tx",
    "modifiedBy": "core:account:System",
    "modifiedOn": 1632589083743,
    "objectId": "core:class:TypeString",
    "objectClass": "core:class:Class",
    "objectSpace": "core:space:Model",
    "mixin": "view:mixin:AttributeEditor",
    "attributes": {
      "editor": "view:component:StringEditor"
    }
  },
  {
    "_id": "614f551ba84d19e0954ba847",
    "_class": "core:class:TxMixin",
    "space": "core:space:Tx",
    "modifiedBy": "core:account:System",
    "modifiedOn": 1632589083743,
    "objectId": "core:class:TypeString",
    "objectClass": "core:class:Class",
    "objectSpace": "core:space:Model",
    "mixin": "view:mixin:AttributePresenter",
    "attributes": {
      "presenter": "view:component:StringPresenter"
    }
  },
  {
    "_id": "614f551ba84d19e0954ba848",
    "_class": "core:class:TxMixin",
    "space": "core:space:Tx",
    "modifiedBy": "core:account:System",
    "modifiedOn": 1632589083743,
    "objectId": "core:class:State",
    "objectClass": "core:class:Class",
    "objectSpace": "core:space:Model",
    "mixin": "view:mixin:AttributePresenter",
    "attributes": {
      "presenter": "view:component:StatePresenter"
    }
  },
  {
    "_id": "614f551ba84d19e0954ba849",
    "_class": "core:class:TxCreateDoc",
    "space": "core:space:Tx",
    "objectId": "view:viewlet:Table",
    "objectClass": "view:class:ViewletDescriptor",
    "objectSpace": "core:space:Model",
    "modifiedOn": 1632589083743,
    "modifiedBy": "core:account:System",
    "attributes": {
      "label": "Table",
      "icon": "view:icon:Table",
      "component": "view:component:TableView"
    }
  },
  {
    "_id": "614f551ba84d19e0954ba84a",
    "_class": "core:class:TxCreateDoc",
    "space": "core:space:Tx",
    "objectId": "view:viewlet:Kanban",
    "objectClass": "view:class:ViewletDescriptor",
    "objectSpace": "core:space:Model",
    "modifiedOn": 1632589083743,
    "modifiedBy": "core:account:System",
    "attributes": {
      "label": "Kanban",
      "icon": "view:icon:Kanban",
      "component": "view:component:KanbanView"
    }
  },
  {
    "_id": "614f551ba84d19e0954ba84b",
    "_class": "core:class:TxCreateDoc",
    "space": "core:space:Tx",
    "objectId": "view:action:Delete",
    "objectClass": "view:class:Action",
    "objectSpace": "core:space:Model",
    "modifiedOn": 1632589083743,
    "modifiedBy": "core:account:System",
    "attributes": {
      "label": "Delete",
      "icon": "view:icon:Kanban",
      "action": "view:actionImpl:Delete"
    }
  },
  {
    "_id": "614f551ba84d19e0954ba84c",
    "_class": "core:class:TxCreateDoc",
    "space": "core:space:Tx",
    "objectId": "614f551ba84d19e0954ba84d",
    "objectClass": "view:class:ActionTarget",
    "objectSpace": "core:space:Model",
    "modifiedOn": 1632589083743,
    "modifiedBy": "core:account:System",
    "attributes": {
      "target": "core:class:Doc",
      "action": "view:action:Delete"
    }
  },
  {
    "_id": "614f551ba84d19e0954ba84e",
    "_class": "core:class:TxCreateDoc",
    "space": "core:space:Tx",
    "objectId": "workbench:mixin:SpaceView",
    "objectClass": "core:class:Class",
    "objectSpace": "core:space:Model",
    "modifiedOn": 1632589083743,
    "modifiedBy": "core:account:System",
    "attributes": {
      "kind": 0,
      "extends": "core:class:Class"
    }
  },
  {
    "_id": "614f551ba84d19e0954ba84f",
    "_class": "core:class:TxCreateDoc",
    "space": "core:space:Tx",
    "objectId": "workbench:class:Application",
    "objectClass": "core:class:Class",
    "objectSpace": "core:space:Model",
    "modifiedOn": 1632589083743,
    "modifiedBy": "core:account:System",
    "attributes": {
      "domain": "model",
      "kind": 0,
      "extends": "core:class:Doc"
    }
  },
  {
    "_id": "614f551ba84d19e0954ba850",
    "_class": "core:class:TxCreateDoc",
    "space": "core:space:Tx",
    "objectId": "contact:class:EmployeeAccount",
    "objectClass": "core:class:Class",
    "objectSpace": "core:space:Model",
    "modifiedOn": 1632589083743,
    "modifiedBy": "core:account:System",
    "attributes": {
      "kind": 0,
      "extends": "core:class:Account"
    }
  },
  {
    "_id": "614f551ba84d19e0954ba851",
    "_class": "core:class:TxCreateDoc",
    "space": "core:space:Tx",
    "objectId": "contact:class:Contact",
    "objectClass": "core:class:Class",
    "objectSpace": "core:space:Model",
    "modifiedOn": 1632589083743,
    "modifiedBy": "core:account:System",
    "attributes": {
      "domain": "contact",
      "kind": 0,
      "extends": "core:class:Doc"
    }
  },
  {
    "_id": "614f551ba84d19e0954ba852",
    "objectId": "614f551ba84d19e0954ba853",
    "_class": "core:class:TxCreateDoc",
    "space": "core:space:Tx",
    "modifiedBy": "core:account:System",
    "modifiedOn": 1632589083567,
    "objectSpace": "core:space:Model",
    "objectClass": "core:class:Attribute",
    "attributes": {
      "name": "channels",
      "type": {
        "_class": "contact:class:TypeChannels"
      },
      "label": "Contact Info",
      "attributeOf": "contact:class:Contact"
    }
  },
  {
    "_id": "614f551ba84d19e0954ba854",
    "_class": "core:class:TxCreateDoc",
    "space": "core:space:Tx",
    "objectId": "contact:class:Person",
    "objectClass": "core:class:Class",
    "objectSpace": "core:space:Model",
    "modifiedOn": 1632589083743,
    "modifiedBy": "core:account:System",
    "attributes": {
      "kind": 0,
      "extends": "contact:class:Contact",
      "label": "Person"
    }
  },
  {
    "_id": "614f551ba84d19e0954ba855",
    "objectId": "614f551ba84d19e0954ba856",
    "_class": "core:class:TxCreateDoc",
    "space": "core:space:Tx",
    "modifiedBy": "core:account:System",
    "modifiedOn": 1632589083567,
    "objectSpace": "core:space:Model",
    "objectClass": "core:class:Attribute",
    "attributes": {
      "name": "firstName",
      "index": 0,
      "type": {
        "_class": "core:class:TypeString"
      },
      "label": "First name",
      "attributeOf": "contact:class:Person"
    }
  },
  {
    "_id": "614f551ba84d19e0954ba857",
    "objectId": "614f551ba84d19e0954ba858",
    "_class": "core:class:TxCreateDoc",
    "space": "core:space:Tx",
    "modifiedBy": "core:account:System",
    "modifiedOn": 1632589083567,
    "objectSpace": "core:space:Model",
    "objectClass": "core:class:Attribute",
    "attributes": {
      "name": "lastName",
      "type": {
        "_class": "core:class:TypeString"
      },
      "label": "Last name",
      "attributeOf": "contact:class:Person"
    }
  },
  {
    "_id": "614f551ba84d19e0954ba859",
    "objectId": "614f551ba84d19e0954ba85a",
    "_class": "core:class:TxCreateDoc",
    "space": "core:space:Tx",
    "modifiedBy": "core:account:System",
    "modifiedOn": 1632589083567,
    "objectSpace": "core:space:Model",
    "objectClass": "core:class:Attribute",
    "attributes": {
      "name": "city",
      "type": {
        "_class": "core:class:TypeString"
      },
      "label": "City",
      "attributeOf": "contact:class:Person"
    }
  },
  {
    "_id": "614f551ba84d19e0954ba85b",
    "_class": "core:class:TxCreateDoc",
    "space": "core:space:Tx",
    "objectId": "contact:class:Employee",
    "objectClass": "core:class:Class",
    "objectSpace": "core:space:Model",
    "modifiedOn": 1632589083743,
    "modifiedBy": "core:account:System",
    "attributes": {
      "kind": 0,
      "extends": "contact:class:Person"
    }
  },
  {
    "_id": "614f551ba84d19e0954ba85c",
    "_class": "core:class:TxCreateDoc",
    "space": "core:space:Tx",
    "objectId": "contact:class:Organization",
    "objectClass": "core:class:Class",
    "objectSpace": "core:space:Model",
    "modifiedOn": 1632589083743,
    "modifiedBy": "core:account:System",
    "attributes": {
      "kind": 0,
      "extends": "contact:class:Contact"
    }
  },
  {
    "_id": "614f551ba84d19e0954ba85d",
    "_class": "core:class:TxCreateDoc",
    "space": "core:space:Tx",
    "objectId": "contact:class:TypeChannels",
    "objectClass": "core:class:Class",
    "objectSpace": "core:space:Model",
    "modifiedOn": 1632589083743,
    "modifiedBy": "core:account:System",
    "attributes": {
      "kind": 0,
      "extends": "core:class:Type"
    }
  },
  {
    "_id": "614f551ba84d19e0954ba85e",
    "_class": "core:class:TxCreateDoc",
    "space": "core:space:Tx",
    "objectId": "contact:class:ChannelProvider",
    "objectClass": "core:class:Class",
    "objectSpace": "core:space:Model",
    "modifiedOn": 1632589083743,
    "modifiedBy": "core:account:System",
    "attributes": {
      "domain": "model",
      "kind": 0,
      "extends": "core:class:Doc"
    }
  },
  {
    "_id": "614f551ba84d19e0954ba85f",
    "_class": "core:class:TxMixin",
    "space": "core:space:Tx",
    "modifiedBy": "core:account:System",
    "modifiedOn": 1632589083743,
    "objectId": "contact:class:TypeChannels",
    "objectClass": "core:class:Class",
    "objectSpace": "core:space:Model",
    "mixin": "view:mixin:AttributePresenter",
    "attributes": {
      "presenter": "contact:component:ChannelsPresenter"
    }
  },
  {
    "_id": "614f551ba84d19e0954ba860",
    "_class": "core:class:TxCreateDoc",
    "space": "core:space:Tx",
    "objectId": "contact:channelProvider:Email",
    "objectClass": "contact:class:ChannelProvider",
    "objectSpace": "core:space:Model",
    "modifiedOn": 1632589083743,
    "modifiedBy": "core:account:System",
    "attributes": {
      "label": "Email",
      "icon": "contact:icon:Email",
      "placeholder": "john.appleseed@apple.com"
    }
  },
  {
    "_id": "614f551ba84d19e0954ba861",
    "_class": "core:class:TxCreateDoc",
    "space": "core:space:Tx",
    "objectId": "614f551ba84d19e0954ba862",
    "objectClass": "contact:class:ChannelProvider",
    "objectSpace": "core:space:Model",
    "modifiedOn": 1632589083743,
    "modifiedBy": "core:account:System",
    "attributes": {
      "label": "Phone",
      "icon": "contact:icon:Phone",
      "placeholder": "+1 555 333 7777"
    }
  },
  {
    "_id": "614f551ba84d19e0954ba863",
    "_class": "core:class:TxCreateDoc",
    "space": "core:space:Tx",
    "objectId": "614f551ba84d19e0954ba864",
    "objectClass": "contact:class:ChannelProvider",
    "objectSpace": "core:space:Model",
    "modifiedOn": 1632589083743,
    "modifiedBy": "core:account:System",
    "attributes": {
      "label": "LinkedIn",
      "icon": "contact:icon:LinkedIn",
      "placeholder": "https://linkedin.com/in/jappleseed"
    }
  },
  {
    "_id": "614f551ba84d19e0954ba865",
    "_class": "core:class:TxCreateDoc",
    "space": "core:space:Tx",
    "objectId": "614f551ba84d19e0954ba866",
    "objectClass": "contact:class:ChannelProvider",
    "objectSpace": "core:space:Model",
    "modifiedOn": 1632589083743,
    "modifiedBy": "core:account:System",
    "attributes": {
      "label": "Twitter",
      "icon": "contact:icon:Twitter",
      "placeholder": "@appleseed"
    }
  },
  {
    "_id": "614f551ba84d19e0954ba867",
    "_class": "core:class:TxCreateDoc",
    "space": "core:space:Tx",
    "objectId": "614f551ba84d19e0954ba868",
    "objectClass": "contact:class:ChannelProvider",
    "objectSpace": "core:space:Model",
    "modifiedOn": 1632589083743,
    "modifiedBy": "core:account:System",
    "attributes": {
      "label": "Telegram",
      "icon": "contact:icon:Telegram",
      "placeholder": "@appleseed"
    }
  },
  {
    "_id": "614f551ba84d19e0954ba869",
    "_class": "core:class:TxCreateDoc",
    "space": "core:space:Tx",
    "objectId": "contact:space:Employee",
    "objectClass": "core:class:Space",
    "objectSpace": "core:space:Model",
    "modifiedOn": 1632589083743,
    "modifiedBy": "core:account:System",
    "attributes": {
      "name": "Employees",
      "description": "Employees",
      "private": false,
      "members": []
    }
  },
  {
    "_id": "614f551ba84d19e0954ba86a",
    "_class": "core:class:TxMixin",
    "space": "core:space:Tx",
    "modifiedBy": "core:account:System",
    "modifiedOn": 1632589083743,
    "objectId": "contact:class:Person",
    "objectClass": "core:class:Class",
    "objectSpace": "core:space:Model",
    "mixin": "view:mixin:AttributePresenter",
    "attributes": {
      "presenter": "contact:component:PersonPresenter"
    }
  },
  {
    "_id": "614f551ba84d19e0954ba86b",
    "_class": "core:class:TxCreateDoc",
    "space": "core:space:Tx",
    "objectId": "chunter:class:Attachment",
    "objectClass": "core:class:Class",
    "objectSpace": "core:space:Model",
    "modifiedOn": 1632589083743,
    "modifiedBy": "core:account:System",
    "attributes": {
      "domain": "attachment",
      "kind": 0,
      "extends": "core:class:Obj"
    }
  },
  {
    "_id": "614f551ba84d19e0954ba86c",
    "_class": "core:class:TxCreateDoc",
    "space": "core:space:Tx",
    "objectId": "chunter:class:Comment",
    "objectClass": "core:class:Class",
    "objectSpace": "core:space:Model",
    "modifiedOn": 1632589083743,
    "modifiedBy": "core:account:System",
    "attributes": {
      "domain": "comment",
      "kind": 0,
      "extends": "core:class:Doc"
    }
  },
  {
    "_id": "614f551ba84d19e0954ba86d",
    "objectId": "614f551ba84d19e0954ba86e",
    "_class": "core:class:TxCreateDoc",
    "space": "core:space:Tx",
    "modifiedBy": "core:account:System",
    "modifiedOn": 1632589083675,
    "objectSpace": "core:space:Model",
    "objectClass": "core:class:Attribute",
    "attributes": {
      "name": "message",
      "index": 0,
      "type": {
        "_class": "core:class:TypeString"
      },
      "label": "Message",
      "attributeOf": "chunter:class:Comment"
    }
  },
  {
    "_id": "614f551ba84d19e0954ba86f",
    "_class": "core:class:TxCreateDoc",
    "space": "core:space:Tx",
    "objectId": "chunter:class:Backlink",
    "objectClass": "core:class:Class",
    "objectSpace": "core:space:Model",
    "modifiedOn": 1632589083743,
    "modifiedBy": "core:account:System",
    "attributes": {
      "kind": 0,
      "extends": "chunter:class:Comment"
    }
  },
  {
    "_id": "614f551ba84d19e0954ba870",
    "_class": "core:class:TxCreateDoc",
    "space": "core:space:Tx",
    "objectId": "chunter:class:Message",
    "objectClass": "core:class:Class",
    "objectSpace": "core:space:Model",
    "modifiedOn": 1632589083743,
    "modifiedBy": "core:account:System",
    "attributes": {
      "domain": "chunter",
      "kind": 0,
      "extends": "core:class:Doc"
    }
  },
  {
    "_id": "614f551ba84d19e0954ba871",
    "objectId": "614f551ba84d19e0954ba872",
    "_class": "core:class:TxCreateDoc",
    "space": "core:space:Tx",
    "modifiedBy": "core:account:System",
    "modifiedOn": 1632589083675,
    "objectSpace": "core:space:Model",
    "objectClass": "core:class:Attribute",
    "attributes": {
      "name": "content",
      "index": 0,
      "type": {
        "_class": "core:class:TypeString"
      },
      "label": "Content",
      "attributeOf": "chunter:class:Message"
    }
  },
  {
    "_id": "614f551ba84d19e0954ba873",
    "_class": "core:class:TxCreateDoc",
    "space": "core:space:Tx",
    "objectId": "chunter:class:Channel",
    "objectClass": "core:class:Class",
    "objectSpace": "core:space:Model",
    "modifiedOn": 1632589083743,
    "modifiedBy": "core:account:System",
    "attributes": {
      "kind": 0,
      "extends": "core:class:Space",
      "label": "chunter:string:Channel",
      "icon": "chunter:icon:Hashtag"
    }
  },
  {
    "_id": "614f551ba84d19e0954ba874",
    "_class": "core:class:TxMixin",
    "space": "core:space:Tx",
    "modifiedBy": "core:account:System",
    "modifiedOn": 1632589083743,
    "objectId": "chunter:class:Channel",
    "objectClass": "core:class:Class",
    "objectSpace": "core:space:Model",
    "mixin": "workbench:mixin:SpaceView",
    "attributes": {
      "view": {
        "class": "chunter:class:Message"
      }
    }
  },
  {
    "_id": "614f551ba84d19e0954ba875",
    "_class": "core:class:TxCreateDoc",
    "space": "core:space:Tx",
    "objectId": "chunter:viewlet:Chat",
    "objectClass": "view:class:ViewletDescriptor",
    "objectSpace": "core:space:Model",
    "modifiedOn": 1632589083743,
    "modifiedBy": "core:account:System",
    "attributes": {
      "label": "Chat",
      "icon": "view:icon:Table",
      "component": "chunter:component:ChannelView"
    }
  },
  {
    "_id": "614f551ba84d19e0954ba876",
    "_class": "core:class:TxCreateDoc",
    "space": "core:space:Tx",
    "objectId": "614f551ba84d19e0954ba877",
    "objectClass": "view:class:Viewlet",
    "objectSpace": "core:space:Model",
    "modifiedOn": 1632589083743,
    "modifiedBy": "core:account:System",
    "attributes": {
      "attachTo": "chunter:class:Message",
      "descriptor": "chunter:viewlet:Chat",
      "open": "X",
      "config": {}
    }
  },
  {
    "_id": "614f551ba84d19e0954ba878",
    "_class": "core:class:TxCreateDoc",
    "space": "core:space:Tx",
    "objectId": "614f551ba84d19e0954ba879",
    "objectClass": "workbench:class:Application",
    "objectSpace": "core:space:Model",
    "modifiedOn": 1632589083743,
    "modifiedBy": "core:account:System",
    "attributes": {
      "label": "chunter:string:ApplicationLabelChunter",
      "icon": "chunter:icon:Chunter",
      "navigatorModel": {
        "spaces": [
          {
            "label": "chunter:string:Channels",
            "spaceClass": "chunter:class:Channel",
            "addSpaceLabel": "chunter:string:CreateChannel",
            "createComponent": "chunter:component:CreateChannel"
          }
        ]
      }
    }
  },
  {
    "_id": "614f551ba84d19e0954ba87a",
    "_class": "core:class:TxCreateDoc",
    "space": "core:space:Tx",
    "objectId": "614f551ba84d19e0954ba87b",
    "objectClass": "chunter:class:Channel",
    "objectSpace": "core:space:Model",
    "modifiedOn": 1632589083743,
    "modifiedBy": "core:account:System",
    "attributes": {
      "name": "general",
      "description": "General Channel",
      "private": false,
      "members": []
    }
  },
  {
    "_id": "614f551ba84d19e0954ba87c",
    "_class": "core:class:TxCreateDoc",
    "space": "core:space:Tx",
    "objectId": "614f551ba84d19e0954ba87d",
    "objectClass": "chunter:class:Channel",
    "objectSpace": "core:space:Model",
    "modifiedOn": 1632589083743,
    "modifiedBy": "core:account:System",
    "attributes": {
      "name": "random",
      "description": "Random Talks",
      "private": false,
      "members": []
    }
  },
  {
    "_id": "614f551ba84d19e0954ba87e",
    "_class": "core:class:TxMixin",
    "space": "core:space:Tx",
    "modifiedBy": "core:account:System",
    "modifiedOn": 1632589083743,
    "objectId": "chunter:class:Attachment",
    "objectClass": "core:class:Class",
    "objectSpace": "core:space:Model",
    "mixin": "view:mixin:AttributePresenter",
    "attributes": {
      "presenter": "chunter:component:AttachmentPresenter"
    }
  },
  {
    "_id": "614f551ba84d19e0954ba87f",
    "_class": "core:class:TxCreateDoc",
    "space": "core:space:Tx",
    "objectId": "task:class:Task",
    "objectClass": "core:class:Class",
    "objectSpace": "core:space:Model",
    "modifiedOn": 1632589083744,
    "modifiedBy": "core:account:System",
    "attributes": {
      "kind": 0,
      "extends": "core:class:Doc"
    }
  },
  {
    "_id": "614f551ba84d19e0954ba880",
    "objectId": "614f551ba84d19e0954ba881",
    "_class": "core:class:TxCreateDoc",
    "space": "core:space:Tx",
    "modifiedBy": "core:account:System",
    "modifiedOn": 1632589083613,
    "objectSpace": "core:space:Model",
    "objectClass": "core:class:Attribute",
    "attributes": {
      "name": "title",
      "type": {
        "_class": "core:class:TypeString"
      },
      "label": "Title",
      "attributeOf": "task:class:Task"
    }
  },
  {
    "_id": "614f551ba84d19e0954ba882",
    "objectId": "614f551ba84d19e0954ba883",
    "_class": "core:class:TxCreateDoc",
    "space": "core:space:Tx",
    "modifiedBy": "core:account:System",
    "modifiedOn": 1632589083613,
    "objectSpace": "core:space:Model",
    "objectClass": "core:class:Attribute",
    "attributes": {
      "name": "description",
      "type": {
        "_class": "core:class:TypeString"
      },
      "label": "Description",
      "attributeOf": "task:class:Task"
    }
  },
  {
    "_id": "614f551ba84d19e0954ba884",
    "objectId": "614f551ba84d19e0954ba885",
    "_class": "core:class:TxCreateDoc",
    "space": "core:space:Tx",
    "modifiedBy": "core:account:System",
    "modifiedOn": 1632589083613,
    "objectSpace": "core:space:Model",
    "objectClass": "core:class:Attribute",
    "attributes": {
      "name": "assignee",
      "type": {
        "_class": "core:class:TypeString"
      },
      "label": "Assignee",
      "attributeOf": "task:class:Task"
    }
  },
  {
    "_id": "614f551ba84d19e0954ba886",
    "_class": "core:class:TxCreateDoc",
    "space": "core:space:Tx",
    "objectId": "task:class:Project",
    "objectClass": "core:class:Class",
    "objectSpace": "core:space:Model",
    "modifiedOn": 1632589083744,
    "modifiedBy": "core:account:System",
    "attributes": {
      "kind": 0,
      "extends": "core:class:Space",
      "label": "Project",
      "icon": "task:icon:Task"
    }
  },
  {
    "_id": "614f551ba84d19e0954ba887",
    "_class": "core:class:TxMixin",
    "space": "core:space:Tx",
    "modifiedBy": "core:account:System",
    "modifiedOn": 1632589083744,
    "objectId": "task:class:Project",
    "objectClass": "core:class:Class",
    "objectSpace": "core:space:Model",
    "mixin": "workbench:mixin:SpaceView",
    "attributes": {
      "view": {
        "class": "task:class:Task",
        "createItemDialog": "task:component:CreateTask"
      }
    }
  },
  {
    "_id": "614f551ba84d19e0954ba888",
    "_class": "core:class:TxCreateDoc",
    "space": "core:space:Tx",
    "objectId": "614f551ba84d19e0954ba889",
    "objectClass": "view:class:Viewlet",
    "objectSpace": "core:space:Model",
    "modifiedOn": 1632589083744,
    "modifiedBy": "core:account:System",
    "attributes": {
      "attachTo": "task:class:Task",
      "descriptor": "view:viewlet:Table",
      "open": "ZX",
      "options": {
        "lookup": {
          "assignee": "contact:class:Employee"
        }
      },
      "config": [
        "title",
        "$lookup.assignee"
      ]
    }
  },
  {
    "_id": "614f551ba84d19e0954ba88a",
    "_class": "core:class:TxCreateDoc",
    "space": "core:space:Tx",
    "objectId": "614f551ba84d19e0954ba88b",
    "objectClass": "workbench:class:Application",
    "objectSpace": "core:space:Model",
    "modifiedOn": 1632589083744,
    "modifiedBy": "core:account:System",
    "attributes": {
      "label": "task:string:ApplicationLabelTask",
      "icon": "task:icon:Task",
      "navigatorModel": {
        "spaces": [
          {
            "label": "task:string:Projects",
            "spaceClass": "task:class:Project",
            "addSpaceLabel": "task:string:CreateProject",
            "createComponent": "task:component:CreateProject"
          }
        ]
      }
    }
  },
  {
    "_id": "614f551ba84d19e0954ba88c",
    "_class": "core:class:TxCreateDoc",
    "space": "core:space:Tx",
    "objectId": "614f551ba84d19e0954ba88d",
    "objectClass": "task:class:Project",
    "objectSpace": "core:space:Model",
    "modifiedOn": 1632589083744,
    "modifiedBy": "core:account:System",
    "attributes": {
      "name": "demo",
      "description": "Demo Project",
      "private": false,
      "members": []
    }
  },
  {
    "_id": "614f551ba84d19e0954ba88e",
    "_class": "core:class:TxCreateDoc",
    "space": "core:space:Tx",
    "objectId": "recruit:class:Applicant",
    "objectClass": "core:class:Class",
    "objectSpace": "core:space:Model",
    "modifiedOn": 1632589083744,
    "modifiedBy": "core:account:System",
    "attributes": {
      "domain": "recruit",
      "kind": 0,
      "extends": "core:class:Doc"
    }
  },
  {
    "_id": "614f551ba84d19e0954ba88f",
    "objectId": "614f551ba84d19e0954ba890",
    "_class": "core:class:TxCreateDoc",
    "space": "core:space:Tx",
    "modifiedBy": "core:account:System",
    "modifiedOn": 1632589083729,
    "objectSpace": "core:space:Model",
    "objectClass": "core:class:Attribute",
    "attributes": {
      "name": "candidate",
      "type": {
        "_class": "core:class:TypeString"
      },
      "label": "Candidate",
      "attributeOf": "recruit:class:Applicant"
    }
  },
  {
    "_id": "614f551ba84d19e0954ba891",
    "objectId": "614f551ba84d19e0954ba892",
    "_class": "core:class:TxCreateDoc",
    "space": "core:space:Tx",
    "modifiedBy": "core:account:System",
    "modifiedOn": 1632589083729,
    "objectSpace": "core:space:Model",
    "objectClass": "core:class:Attribute",
    "attributes": {
      "name": "state",
      "type": {
        "_class": "core:class:TypeString"
      },
      "label": "State",
      "attributeOf": "recruit:class:Applicant"
    }
  },
  {
    "_id": "614f551ba84d19e0954ba893",
    "_class": "core:class:TxCreateDoc",
    "space": "core:space:Tx",
    "objectId": "recruit:class:Candidate",
    "objectClass": "core:class:Class",
    "objectSpace": "core:space:Model",
    "modifiedOn": 1632589083744,
    "modifiedBy": "core:account:System",
    "attributes": {
      "kind": 0,
      "extends": "contact:class:Person",
      "label": "Candidate"
    }
  },
  {
    "_id": "614f551ba84d19e0954ba894",
    "objectId": "614f551ba84d19e0954ba895",
    "_class": "core:class:TxCreateDoc",
    "space": "core:space:Tx",
    "modifiedBy": "core:account:System",
    "modifiedOn": 1632589083729,
    "objectSpace": "core:space:Model",
    "objectClass": "core:class:Attribute",
    "attributes": {
      "name": "title",
      "type": {
        "_class": "core:class:TypeString"
      },
      "label": "Title",
      "attributeOf": "recruit:class:Candidate"
    }
  },
  {
    "_id": "614f551ba84d19e0954ba896",
    "objectId": "614f551ba84d19e0954ba897",
    "_class": "core:class:TxCreateDoc",
    "space": "core:space:Tx",
    "modifiedBy": "core:account:System",
    "modifiedOn": 1632589083729,
    "objectSpace": "core:space:Model",
    "objectClass": "core:class:Attribute",
    "attributes": {
      "name": "attachments",
      "type": {
        "_class": "core:class:Bag"
      },
      "label": "Attachments",
      "attributeOf": "recruit:class:Candidate"
    }
  },
  {
    "_id": "614f551ba84d19e0954ba898",
    "_class": "core:class:TxCreateDoc",
    "space": "core:space:Tx",
    "objectId": "recruit:class:Candidates",
    "objectClass": "core:class:Class",
    "objectSpace": "core:space:Model",
    "modifiedOn": 1632589083744,
    "modifiedBy": "core:account:System",
    "attributes": {
      "kind": 0,
      "extends": "core:class:Space",
      "label": "recruit:string:CandidatePools",
      "icon": "recruit:icon:RecruitApplication"
    }
  },
  {
    "_id": "614f551ba84d19e0954ba899",
    "_class": "core:class:TxCreateDoc",
    "space": "core:space:Tx",
    "objectId": "recruit:class:Vacancy",
    "objectClass": "core:class:Class",
    "objectSpace": "core:space:Model",
    "modifiedOn": 1632589083744,
    "modifiedBy": "core:account:System",
    "attributes": {
      "kind": 0,
      "extends": "core:class:SpaceWithStates",
      "label": "recruit:string:Vacancy",
      "icon": "recruit:icon:Vacancy"
    }
  },
  {
    "_id": "614f551ba84d19e0954ba89a",
    "_class": "core:class:TxMixin",
    "space": "core:space:Tx",
    "modifiedBy": "core:account:System",
    "modifiedOn": 1632589083744,
    "objectId": "recruit:class:Vacancy",
    "objectClass": "core:class:Class",
    "objectSpace": "core:space:Model",
    "mixin": "workbench:mixin:SpaceView",
    "attributes": {
      "view": {
        "class": "recruit:class:Applicant",
        "createItemDialog": "recruit:component:CreateApplication"
      }
    }
  },
  {
    "_id": "614f551ba84d19e0954ba89b",
    "_class": "core:class:TxMixin",
    "space": "core:space:Tx",
    "modifiedBy": "core:account:System",
    "modifiedOn": 1632589083744,
    "objectId": "recruit:class:Candidates",
    "objectClass": "core:class:Class",
    "objectSpace": "core:space:Model",
    "mixin": "workbench:mixin:SpaceView",
    "attributes": {
      "view": {
        "class": "recruit:class:Candidate",
        "createItemDialog": "recruit:component:CreateCandidate"
      }
    }
  },
  {
    "_id": "614f551ba84d19e0954ba89c",
    "_class": "core:class:TxCreateDoc",
    "space": "core:space:Tx",
    "objectId": "614f551ba84d19e0954ba89d",
    "objectClass": "workbench:class:Application",
    "objectSpace": "core:space:Model",
    "modifiedOn": 1632589083744,
    "modifiedBy": "core:account:System",
    "attributes": {
      "label": "recruit:string:RecruitApplication",
      "icon": "recruit:icon:RecruitApplication",
      "navigatorModel": {
        "spaces": [
          {
            "label": "recruit:string:Vacancies",
            "spaceClass": "recruit:class:Vacancy",
            "addSpaceLabel": "recruit:string:CreateVacancy",
            "createComponent": "recruit:component:CreateVacancy"
          },
          {
            "label": "recruit:string:CandidatePools",
            "spaceClass": "recruit:class:Candidates",
            "addSpaceLabel": "recruit:string:CreateCandidates",
            "createComponent": "recruit:component:CreateCandidates"
          }
        ]
      }
    }
  },
  {
    "_id": "614f551ba84d19e0954ba89e",
    "_class": "core:class:TxCreateDoc",
    "space": "core:space:Tx",
    "objectId": "recruit:space:CandidatesPublic",
    "objectClass": "recruit:class:Candidates",
    "objectSpace": "core:space:Model",
    "modifiedOn": 1632589083744,
    "modifiedBy": "core:account:System",
    "attributes": {
      "name": "public",
      "description": "Public Candidates",
      "private": false,
      "members": []
    }
  },
  {
    "_id": "614f551ba84d19e0954ba89f",
    "_class": "core:class:TxCreateDoc",
    "space": "core:space:Tx",
    "objectId": "614f551ba84d19e0954ba8a0",
    "objectClass": "view:class:Viewlet",
    "objectSpace": "core:space:Model",
    "modifiedOn": 1632589083744,
    "modifiedBy": "core:account:System",
    "attributes": {
      "attachTo": "recruit:class:Candidate",
      "descriptor": "view:viewlet:Table",
      "open": "recruit:component:EditCandidate",
      "options": {},
      "config": [
        "",
        "#recruit:component:CreateApplicationPresenter/Action",
        "title",
        "city",
        "#chunter:component:AttachmentPresenter/Files",
        "channels"
      ]
    }
  },
  {
    "_id": "614f551ba84d19e0954ba8a1",
    "_class": "core:class:TxCreateDoc",
    "space": "core:space:Tx",
    "objectId": "614f551ba84d19e0954ba8a2",
    "objectClass": "view:class:Viewlet",
    "objectSpace": "core:space:Model",
    "modifiedOn": 1632589083744,
    "modifiedBy": "core:account:System",
    "attributes": {
      "attachTo": "recruit:class:Applicant",
      "descriptor": "view:viewlet:Table",
      "open": "recruit:component:EditCandidate",
      "options": {
        "lookup": {
          "candidate": "recruit:class:Candidate",
          "state": "core:class:State"
        }
      },
      "config": [
        "$lookup.candidate",
        "#recruit:component:ApplicationPresenter/Application",
        "$lookup.state",
        "$lookup.candidate.city",
        "$lookup.candidate.channels"
      ]
    }
  },
  {
    "_id": "614f551ba84d19e0954ba8a3",
    "_class": "core:class:TxCreateDoc",
    "space": "core:space:Tx",
    "objectId": "614f551ba84d19e0954ba8a4",
    "objectClass": "view:class:Viewlet",
    "objectSpace": "core:space:Model",
    "modifiedOn": 1632589083744,
    "modifiedBy": "core:account:System",
    "attributes": {
      "attachTo": "recruit:class:Applicant",
      "descriptor": "view:viewlet:Kanban",
      "open": "recruit:component:EditCandidate",
      "options": {
        "lookup": {
          "candidate": "recruit:class:Candidate",
          "state": "core:class:State"
        }
      },
      "config": [
        "$lookup.candidate",
        "$lookup.state",
        "$lookup.candidate.city",
        "$lookup.candidate.channels"
      ]
    }
  },
  {
    "_id": "614f551ba84d19e0954ba8a5",
    "_class": "core:class:TxMixin",
    "space": "core:space:Tx",
    "modifiedBy": "core:account:System",
    "modifiedOn": 1632589083744,
    "objectId": "recruit:class:Applicant",
    "objectClass": "core:class:Class",
    "objectSpace": "core:space:Model",
    "mixin": "view:mixin:KanbanCard",
    "attributes": {
      "card": "recruit:component:KanbanCard"
    }
  },
  {
    "_id": "614f551ba84d19e0954ba8a6",
    "_class": "core:class:TxMixin",
    "space": "core:space:Tx",
    "modifiedBy": "core:account:System",
    "modifiedOn": 1632589083744,
    "objectId": "recruit:class:Candidate",
    "objectClass": "core:class:Class",
    "objectSpace": "core:space:Model",
    "mixin": "view:mixin:ObjectEditor",
    "attributes": {
      "editor": "recruit:component:EditCandidate"
    }
  },
  {
    "_id": "614f551ba84d19e0954ba8a7",
    "_class": "core:class:TxCreateDoc",
    "space": "core:space:Tx",
    "objectId": "server-core:class:Trigger",
    "objectClass": "core:class:Class",
    "objectSpace": "core:space:Model",
    "modifiedOn": 1632589083744,
    "modifiedBy": "core:account:System",
    "attributes": {
      "domain": "model",
      "kind": 0,
      "extends": "core:class:Doc"
    }
  },
  {
    "_id": "614f551ba84d19e0954ba8a8",
    "_class": "core:class:TxCreateDoc",
    "space": "core:space:Tx",
    "objectId": "614f551ba84d19e0954ba8a9",
    "objectClass": "server-core:class:Trigger",
    "objectSpace": "core:space:Model",
    "modifiedOn": 1632589083744,
    "modifiedBy": "core:account:System",
    "attributes": {
      "trigger": "server-chunter:trigger:OnMessage"
    }
  },
  {
    "_id": "614f551ba84d19e0954ba8ab",
    "_class": "core:class:TxCreateDoc",
    "space": "core:space:Tx",
    "objectId": "614f551ba84d19e0954ba8aa",
    "objectClass": "contact:class:Employee",
    "objectSpace": "contact:space:Employee",
    "modifiedOn": 1632589083744,
    "modifiedBy": "core:account:System",
    "attributes": {
      "firstName": "Rosamund",
      "lastName": "Chen",
      "city": "Mountain View",
      "channels": []
    }
  },
  {
    "_id": "614f551ba84d19e0954ba8ac",
    "_class": "core:class:TxCreateDoc",
    "space": "core:space:Tx",
    "objectId": "614f551ba84d19e0954ba8ad",
    "objectClass": "contact:class:EmployeeAccount",
    "objectSpace": "core:space:Model",
    "modifiedOn": 1632589083744,
    "modifiedBy": "core:account:System",
    "attributes": {
      "email": "rosamund@hc.engineering",
      "employee": "614f551ba84d19e0954ba8aa",
      "firstName": "Rosamund",
      "lastName": "Chen"
    }
  },
  {
    "_id": "614f551ba84d19e0954ba8ae",
    "_class": "core:class:TxCreateDoc",
    "space": "core:space:Tx",
    "objectId": "614f551ba84d19e0954ba8af",
    "objectClass": "recruit:class:Candidate",
    "objectSpace": "recruit:space:CandidatesPublic",
    "modifiedOn": 1632589083744,
    "modifiedBy": "core:account:System",
    "attributes": {
      "firstName": "Andrey",
      "lastName": "P.",
      "city": "Monte Carlo",
      "channels": [
        {
          "provider": "contact:channelProvider:Email",
          "value": "andrey@hc.engineering"
        }
      ],
      "attachments": {}
    }
  },
  {
    "_id": "614f551ba84d19e0954ba8b0",
    "_class": "core:class:TxCreateDoc",
    "space": "core:space:Tx",
    "objectId": "614f551ba84d19e0954ba8b1",
    "objectClass": "recruit:class:Candidate",
    "objectSpace": "recruit:space:CandidatesPublic",
    "modifiedOn": 1632589083744,
    "modifiedBy": "core:account:System",
    "attributes": {
      "firstName": "Marina",
      "lastName": "M.",
      "city": "Los Angeles",
      "channels": [
        {
          "provider": "contact:channelProvider:Email",
          "value": "marina@hc.engineering"
        }
      ],
      "attachments": {}
    }
  }
]